alipay_faas_client_sdk/__init__.py
alipay_faas_client_sdk/cloud.py
alipay_faas_client_sdk/function/__init__.py
alipay_faas_client_sdk/function/fn_client.py
alipay_faas_client_sdk/function/fn_request.py
alipay_faas_client_sdk/function/fn_response.py
alipay_faas_client_sdk/http/__init__.py
alipay_faas_client_sdk/http/http_client.py
alipay_faas_client_sdk/http/http_constants.py
alipay_faas_client_sdk/http/http_request.py
alipay_faas_client_sdk/http/http_response.py
alipay_faas_client_sdk/utils/__init__.py
alipay_faas_client_sdk/utils/env_util.py
alipay_faas_client_sdk/utils/hash_util.py
alipay_faas_client_sdk-0.0.1.dist-info/LICENSE
alipay_faas_client_sdk-0.0.1.dist-info/METADATA
alipay_faas_client_sdk-0.0.1.dist-info/WHEEL
alipay_faas_client_sdk-0.0.1.dist-info/top_level.txt
alipay_faas_client_sdk-0.0.1.dist-info/RECORD
