Metadata-Version: 2.1
Name: alipay-faas-client-sdk
Version: 0.0.1
Summary: Alipay FaaS Client SDK
Home-page: https://cloud.alipay.com
Author: QiYuan
Author-email: lj162403@alipay.com
Project-URL: Site, https://cloud.alipay.com
Project-URL: Repo, https://cloud.alipay.com
Project-URL: Documentation, https://opendocs.alipay.com/mini/089c99?pathHash=5a879d9a
Platform: all
Classifier: Intended Audience :: Developers
Classifier: Operating System :: OS Independent
Classifier: License :: OSI Approved :: MIT License
Classifier: Programming Language :: Python
Classifier: Programming Language :: Python :: 3
Classifier: Programming Language :: Python :: 3.9
Classifier: Programming Language :: Python :: 3.10
Classifier: Programming Language :: Python :: 3.11
Classifier: Topic :: Software Development :: Libraries
Requires-Python: >=3.9.0
License-File: LICENSE
Requires-Dist: requests
